squiral/__init__.py
squiral/__main__.py
squiral/main.py
squiral/squiral.py
squiral-0.5.0.dist-info/LICENSE
squiral-0.5.0.dist-info/METADATA
squiral-0.5.0.dist-info/WHEEL
squiral-0.5.0.dist-info/entry_points.txt
squiral-0.5.0.dist-info/RECORD
