Metadata-Version: 2.1
Name: squiral
Version: 0.5.0
Summary: squiral - square spiral
Home-page: https://github.com/sadikkuzu/squiral
License: MIT
Author: SADIK KUZU
Author-email: sadikkuzu@hotmail.com
Requires-Python: >=3.8,<4.0
Classifier: License :: OSI Approved :: MIT License
Classifier: Programming Language :: Python :: 3
Classifier: Programming Language :: Python :: 3.8
Classifier: Programming Language :: Python :: 3.9
Classifier: Programming Language :: Python :: 3.10
Classifier: Programming Language :: Python :: 3.11
Classifier: Programming Language :: Python :: 3.12
